README.md
setup.py
scikit_discovery.egg-info/PKG-INFO
scikit_discovery.egg-info/SOURCES.txt
scikit_discovery.egg-info/dependency_links.txt
scikit_discovery.egg-info/not-zip-safe
scikit_discovery.egg-info/requires.txt
scikit_discovery.egg-info/top_level.txt
skdiscovery/__init__.py
skdiscovery/data_structure/__init__.py
skdiscovery/data_structure/framework/__init__.py
skdiscovery/data_structure/framework/base.py
skdiscovery/data_structure/framework/config.py
skdiscovery/data_structure/framework/discoverypipeline.py
skdiscovery/data_structure/framework/stagecontainers.py
skdiscovery/data_structure/generic/__init__.py
skdiscovery/data_structure/generic/accumulators/__init__.py
skdiscovery/data_structure/generic/accumulators/data.py
skdiscovery/data_structure/generic/accumulators/gpshplotter.py
skdiscovery/data_structure/generic/accumulators/hcluster.py
skdiscovery/data_structure/image/__init__.py
skdiscovery/data_structure/image/accumulators/__init__.py
skdiscovery/data_structure/image/accumulators/saver.py
skdiscovery/data_structure/image/analysis/__init__.py
skdiscovery/data_structure/image/analysis/squares_from_poly.py
skdiscovery/data_structure/image/filters/__init__.py
skdiscovery/data_structure/image/filters/select_channel.py
skdiscovery/data_structure/image/generate/__init__.py
skdiscovery/data_structure/image/generate/rotate_image.py
skdiscovery/data_structure/image/generate/tile_image.py
skdiscovery/data_structure/series/__init__.py
skdiscovery/data_structure/series/accumulators/__init__.py
skdiscovery/data_structure/series/accumulators/plotter.py
skdiscovery/data_structure/series/analysis/__init__.py
skdiscovery/data_structure/series/analysis/correlate.py
skdiscovery/data_structure/series/analysis/gca.py
skdiscovery/data_structure/series/analysis/mogi.py
skdiscovery/data_structure/series/filters/__init__.py
skdiscovery/data_structure/series/filters/dataremover.py
skdiscovery/data_structure/series/filters/hyperbolictan.py
skdiscovery/data_structure/series/filters/interpolate.py
skdiscovery/data_structure/series/filters/kalman.py
skdiscovery/data_structure/series/filters/lowpass.py
skdiscovery/data_structure/series/filters/median.py
skdiscovery/data_structure/series/filters/offset_detrend.py
