Metadata-Version: 2.1
Name: scikit-discovery
Version: 0.9.18
Summary: A package for Computer-Aided Discovery
Home-page: https://github.com/MITHaystack/scikit-discovery
Author: MITHAGI
Author-email: skdaccess@mit.edu
License: UNKNOWN
Platform: UNKNOWN
Classifier: Topic :: Scientific/Engineering
Classifier: Intended Audience :: Science/Research
Classifier: License :: OSI Approved :: MIT License
Classifier: License :: OSI Approved :: GNU Library or Lesser General Public License (LGPL)
Classifier: Programming Language :: Python :: 3 :: Only
Requires-Python: >=3.4
